selmate/__init__.py
selmate/composites.py
selmate/constants.py
selmate/humanity/constants.py
selmate/humanity/latency.py
selmate/js_primitives.py
selmate/safe_exceptions.py
selmate/selenium_primitives.py
selmate/utils.py
selmate-1.3.2.dist-info/LICENSE
selmate-1.3.2.dist-info/METADATA
selmate-1.3.2.dist-info/WHEEL
selmate-1.3.2.dist-info/RECORD
