Metadata-Version: 2.3
Name: selmate
Version: 1.3.2
Summary: A utility library for Selenium WebDriver to enable human-like interactions, robust exception handling, and web automation tasks like popup handling and URL normalization.
License: MIT License
Keywords: selenium,web automation,human-like,web scraping,browser automation,popup handling,url normalization,testing
Author: FINWAX
Author-email: waxbid@gmail.com
Requires-Python: >=3.10
Classifier: Development Status :: 5 - Production/Stable
Classifier: Intended Audience :: Developers
Classifier: Topic :: Software Development :: Testing
Classifier: Topic :: Software Development :: Libraries :: Python Modules
Classifier: License :: OSI Approved :: MIT License
Classifier: Programming Language :: Python :: 3
Classifier: Programming Language :: Python :: 3.10
Classifier: Programming Language :: Python :: 3.11
Classifier: Programming Language :: Python :: 3.12
Classifier: Operating System :: OS Independent
Requires-Dist: beautifulsoup4 (>=4.13.4,<5.0.0)
Requires-Dist: lxml (>=5.4.0,<6.0.0)
Requires-Dist: rapidfuzz (>=3.13.0,<4.0.0)
Requires-Dist: selenium (>=4.33.0,<5.0.0)
Project-URL: Homepage, https://github.com/FINWAX/selmate.py
Project-URL: Repository, https://github.com/FINWAX/selmate.py
